generation_generators/__init__.py
generation_generators/f_score_generator.py
generation_generators/vanilla_generator.py
genetic_feature_selection/__init__.py
genetic_feature_selection/f_score_generator.py
genetic_feature_selection/genetic_feature_selection.py
genetic_feature_selection/genetic_funcs.py
genetic_feature_selection/genetic_iter.py
genetic_feature_selection/genetic_search.py
genetic_feature_selection/genetic_stats.py
genetic_feature_selection/roulette_wheel_selection.py
genetic_feature_selection/vanilla_generator.py
mating/__init__.py
mating/roulette_wheel_selection.py
utils/__init__.py
utils/log_utils.py
genetic_feature_selection-0.1.8.dist-info/METADATA
genetic_feature_selection-0.1.8.dist-info/WHEEL
genetic_feature_selection-0.1.8.dist-info/top_level.txt
genetic_feature_selection-0.1.8.dist-info/RECORD
